retracesoftware/stableset.cpython-311-darwin.so
retracesoftware_stableset-0.1.3.dist-info/RECORD
retracesoftware_stableset-0.1.3.dist-info/WHEEL
retracesoftware_stableset-0.1.3.dist-info/METADATA
