Metadata-Version: 2.1
Name: retracesoftware.stableset
Version: 0.1.3
Summary: C-Extension type for python that provides a set implementation that is stable on iteration
Keywords: set,stable,iteration,c-extension,data-structure
Author-Email: Retrace Software <info@retracesoftware.com>
Maintainer-Email: Retrace Software <info@retracesoftware.com>
License: Apache-2.0
Classifier: Development Status :: 4 - Beta
Classifier: Intended Audience :: Developers
Classifier: License :: OSI Approved :: Apache Software License
Classifier: Operating System :: OS Independent
Classifier: Programming Language :: Python :: 3
Classifier: Programming Language :: Python :: 3.11
Classifier: Programming Language :: Python :: Implementation :: CPython
Classifier: Topic :: Software Development :: Libraries :: Python Modules
Classifier: Topic :: Scientific/Engineering :: Information Analysis
Project-URL: Homepage, https://github.com/retracesoftware/stableset
Project-URL: Repository, https://github.com/retracesoftware/stableset
Project-URL: Documentation, https://github.com/retracesoftware/stableset
Project-URL: Bug Tracker, https://github.com/retracesoftware/stableset/issues
Requires-Python: >=3.11
